tzolkin_calendar/__init__.py
tzolkin_calendar/__main__.py
tzolkin_calendar/calculate.py
tzolkin_calendar/commandline.py
tzolkin_calendar/main.py
tzolkin_calendar/tzolkin.py
tzolkin_calendar/doc/doctrees/Tzolk’in Calender Python Module.doctree
tzolkin_calendar/doc/doctrees/Tzolk’in Command Line.doctree
tzolkin_calendar/doc/doctrees/contributing.doctree
tzolkin_calendar/doc/doctrees/environment.pickle
tzolkin_calendar/doc/doctrees/genindex.doctree
tzolkin_calendar/doc/doctrees/index.doctree
tzolkin_calendar/doc/doctrees/installation.doctree
tzolkin_calendar/doc/doctrees/jupyter_notebook.doctree
tzolkin_calendar/doc/doctrees/license.doctree
tzolkin_calendar/doc/doctrees/modules.doctree
tzolkin_calendar/doc/doctrees/py-modindex.doctree
tzolkin_calendar/doc/doctrees/tzolkin_calendar.doctree
tzolkin_calendar/doc/html/.buildinfo
tzolkin_calendar/doc/html/Tzolk’in Calender Python Module.html
tzolkin_calendar/doc/html/Tzolk’in Command Line.html
tzolkin_calendar/doc/html/contributing.html
tzolkin_calendar/doc/html/genindex.html
tzolkin_calendar/doc/html/index.html
tzolkin_calendar/doc/html/installation.html
tzolkin_calendar/doc/html/jupyter_notebook.html
tzolkin_calendar/doc/html/license.html
tzolkin_calendar/doc/html/modules.html
tzolkin_calendar/doc/html/objects.inv
tzolkin_calendar/doc/html/py-modindex.html
tzolkin_calendar/doc/html/search.html
tzolkin_calendar/doc/html/searchindex.js
tzolkin_calendar/doc/html/tzolkin_calendar.html
tzolkin_calendar/doc/html/_images/tzolkin_jupyter_page.png
tzolkin_calendar/doc/html/_static/_sphinx_javascript_frameworks_compat.js
tzolkin_calendar/doc/html/_static/basic.css
tzolkin_calendar/doc/html/_static/doctools.js
tzolkin_calendar/doc/html/_static/documentation_options.js
tzolkin_calendar/doc/html/_static/file.png
tzolkin_calendar/doc/html/_static/jquery.js
tzolkin_calendar/doc/html/_static/language_data.js
tzolkin_calendar/doc/html/_static/minus.png
tzolkin_calendar/doc/html/_static/plus.png
tzolkin_calendar-1.0.2.dist-info/LICENSE
tzolkin_calendar-1.0.2.dist-info/METADATA
tzolkin_calendar-1.0.2.dist-info/WHEEL
tzolkin_calendar-1.0.2.dist-info/top_level.txt
tzolkin_calendar-1.0.2.dist-info/RECORD
