Metadata-Version: 2.1
Name: tzolkin-calendar
Version: 1.0.2
Summary: Program to calculate and convert Tzolk’in/Maya calendar dates.
Home-page: https://codeberg.org/Release-Candidate/tzolkin-calendar
Author: Release-Candidate
Author-email: rec@gmx.at
Project-URL: Bug Tracker, https://codeberg.org/Release-Candidate/tzolkin-calendar/issues
Project-URL: Documentation, https://tzolkin-calendar.readthedocs.io/en/latest/
Keywords: Maya,Tzolkin,Tzolk’in,calendar
Classifier: Programming Language :: Python :: 3 :: Only
Classifier: Programming Language :: Python :: 3.8
Classifier: Programming Language :: Python :: 3.9
Classifier: License :: OSI Approved :: MIT License
Classifier: Operating System :: MacOS :: MacOS X
Classifier: Operating System :: Microsoft :: Windows
Classifier: Operating System :: POSIX :: Linux
Classifier: Operating System :: POSIX
Classifier: Operating System :: POSIX :: BSD
Classifier: Operating System :: Unix
Classifier: Operating System :: OS Independent
Classifier: Environment :: Console
Classifier: Development Status :: 5 - Production/Stable
Classifier: Intended Audience :: Developers
Classifier: Topic :: Software Development :: Libraries :: Python Modules
Classifier: Intended Audience :: End Users/Desktop
Requires-Python: >=3.8
License-File: LICENSE
